Metadata-Version: 2.1
Name: pyNamespace
Version: 0.0.7
Summary: Filesystem-like hierarhy of objects and it's namespace
Home-page: https://github.com/vulogov/pyNamespace
Author: Vladimir Ulogov
Author-email: vladimir.ulogov@me.com
License: GPL3
Platform: UNKNOWN
Classifier: Programming Language :: Python :: 3
Classifier: Development Status :: 3 - Alpha
Classifier: Intended Audience :: Information Technology
Classifier: License :: OSI Approved :: GNU General Public License v3 (GPLv3)
Classifier: Operating System :: OS Independent
Classifier: Topic :: Software Development :: Libraries
Classifier: Topic :: Software Development :: Libraries :: Application Frameworks
Requires-Python: >=3.6
